nuit/__init__.py
nuit/constants.py
nuit/helpers.py
nuit/histogram.py
nuit/model.py
nuit/output.py
nuit/data/__init__.py
nuit/data/classes.py
nuit/data/isolib.py
nuit/data/mgxslib.py
nuit/data/xslib.py
NUIT-0.3.dist-info/LICENCE
NUIT-0.3.dist-info/METADATA
NUIT-0.3.dist-info/WHEEL
NUIT-0.3.dist-info/top_level.txt
NUIT-0.3.dist-info/RECORD
