Metadata-Version: 2.1
Name: NUIT
Version: 0.3
Summary: Wrapper for source term alaysis code NUIT
Home-page: https://github.com/thu-inet/pyNUIT
Author: THU-RSAG
Author-email: z-wj21@mails.tsinghua.edu.cn
Classifier: Development Status :: 3 - Alpha
Classifier: Programming Language :: Python :: 3
Classifier: License :: OSI Approved :: MIT License
Classifier: Operating System :: OS Independent
License-File: LICENCE
Requires-Dist: numpy (>=1.26.0)
Requires-Dist: pandas (>=2.1.3)
Requires-Dist: matplotlib (>=3.8.2)
